poetry_2_conflict_svltv32/__init__.py
poetry_2_conflict_svltv32/conflict2.py
poetry_2_conflict_svltv32-0.4.0.dist-info/WHEEL
poetry_2_conflict_svltv32-0.4.0.dist-info/METADATA
poetry_2_conflict_svltv32-0.4.0.dist-info/RECORD
