Metadata-Version: 2.1
Name: poetry-2-conflict-svltv32
Version: 0.4.0
Summary: 
Author: Test
Requires-Python: >=3.8,<4.0
Classifier: Programming Language :: Python :: 3
Classifier: Programming Language :: Python :: 3.8
Classifier: Programming Language :: Python :: 3.9
Requires-Dist: poetry_1_conflict_svltv32
